pybusinesscentral/__init__.py
pybusinesscentral/api_client.py
pybusinesscentral/api_response.py
pybusinesscentral/configuration.py
pybusinesscentral/exceptions.py
pybusinesscentral/py.typed
pybusinesscentral/rest.py
pybusinesscentral/api/__init__.py
pybusinesscentral/api/account_api.py
pybusinesscentral/api/company_api.py
pybusinesscentral/api/customer_api.py
pybusinesscentral/api/default_api.py
pybusinesscentral/api/dimension_api.py
pybusinesscentral/api/dimension_set_line_api.py
pybusinesscentral/api/payment_term_api.py
pybusinesscentral/api/purchase_invoice_api.py
pybusinesscentral/api/purchase_invoice_line_api.py
pybusinesscentral/api/sales_credit_memo_api.py
pybusinesscentral/api/sales_credit_memo_line_api.py
pybusinesscentral/api/sales_invoice_api.py
pybusinesscentral/api/sales_invoice_line_api.py
pybusinesscentral/api/vendor_api.py
pybusinesscentral/apis/__init__.py
pybusinesscentral/model/__init__.py
pybusinesscentral/model/account.py
pybusinesscentral/model/aged_accounts_payable.py
pybusinesscentral/model/aged_accounts_receivable.py
pybusinesscentral/model/attachments.py
pybusinesscentral/model/balance_sheet.py
pybusinesscentral/model/bank_account.py
pybusinesscentral/model/cash_flow_statement.py
pybusinesscentral/model/company.py
pybusinesscentral/model/company_information.py
pybusinesscentral/model/country_region.py
pybusinesscentral/model/currency.py
pybusinesscentral/model/customer.py
pybusinesscentral/model/customer_financial_detail.py
pybusinesscentral/model/customer_payment.py
pybusinesscentral/model/customer_payment_journal.py
pybusinesscentral/model/customer_sale.py
pybusinesscentral/model/default_dimensions.py
pybusinesscentral/model/dimension.py
pybusinesscentral/model/dimension_line.py
pybusinesscentral/model/dimension_set_line.py
pybusinesscentral/model/dimension_value.py
pybusinesscentral/model/dimensiontype.py
pybusinesscentral/model/documentlineobjectdetailstype.py
pybusinesscentral/model/employee.py
pybusinesscentral-3.9.0.dist-info/METADATA
pybusinesscentral-3.9.0.dist-info/WHEEL
pybusinesscentral-3.9.0.dist-info/top_level.txt
pybusinesscentral-3.9.0.dist-info/RECORD
