Metadata-Version: 2.4
Name: pybusinesscentral
Version: 3.9.0
Summary: (v2.0) Dynamics 365 Business Central
Home-page: 
Author: Uptick
Author-email: support@uptickhq.com
Keywords: OpenAPI,OpenAPI-Generator,(v2.0) Dynamics 365 Business Central
Requires-Dist: urllib3<3.0.0,>=2.1.0
Requires-Dist: python-dateutil>=2.8.2
Requires-Dist: pydantic>=2
Requires-Dist: typing-extensions>=4.7.1
Dynamic: author
Dynamic: author-email
Dynamic: description
Dynamic: description-content-type
Dynamic: keywords
Dynamic: requires-dist
Dynamic: summary
